CHANGES.txt
LICENSE.txt
MANIFEST.in
README.md
README_pypi.txt
setup.py
side_effect_containers/__init__.py
side_effect_containers/containers.py
side_effect_containers.egg-info/PKG-INFO
side_effect_containers.egg-info/SOURCES.txt
side_effect_containers.egg-info/dependency_links.txt
side_effect_containers.egg-info/top_level.txt