Metadata-Version: 1.0
Name: side-effect-containers
Version: 1.0
Summary: Containers that do a side-effect when an item is added or removed.
Home-page: https://github.com/jmatthias/side_effect_containers
Author: Josh Matthias
Author-email: jmatthias4570@gmail.com
License: LICENSE.txt
Platform: UNKNOWN
